deutschebahn/__init__.py
deutschebahn/db_infoscreen.py
deutschebahn/ds100.csv
deutschebahn/ds100.py
deutschebahn/fahrplan.py
deutschebahn/metadata.py
deutschebahn/utils/__init__.py
deutschebahn/utils/utils.py
deutschebahn-1.4.0.dist-info/LICENSE
deutschebahn-1.4.0.dist-info/METADATA
deutschebahn-1.4.0.dist-info/WHEEL
deutschebahn-1.4.0.dist-info/top_level.txt
deutschebahn-1.4.0.dist-info/RECORD
