Metadata-Version: 2.1
Name: deutschebahn
Version: 1.4.0
Summary: Collection of utilities related to German train operator Deutsche Bahn.
Requires-Dist: requests
